zerotk.xml_factory-0.1.2-py2.7-nspkg.pth
zerotk/string.py
zerotk/xml_factory/__init__.py
zerotk/xml_factory/_pretty_xml.py
zerotk/xml_factory/_xml_factory.py
zerotk.xml_factory-0.1.2.dist-info/DESCRIPTION.rst
zerotk.xml_factory-0.1.2.dist-info/METADATA
zerotk.xml_factory-0.1.2.dist-info/RECORD
zerotk.xml_factory-0.1.2.dist-info/WHEEL
zerotk.xml_factory-0.1.2.dist-info/metadata.json
zerotk.xml_factory-0.1.2.dist-info/namespace_packages.txt
zerotk.xml_factory-0.1.2.dist-info/top_level.txt
