Metadata-Version: 2.0
Name: zerotk.xml-factory
Version: 0.1.2
Summary: XML/Dict/Json Generator.
Home-page: https://github.com/zerotk/reraiseit
Author: Alexandre Andrade, Diogo de Campos
Author-email: kaniabi@gmail.com, campos.ddc@gmail.com
License: UNKNOWN
Keywords: xml,dict,json,generator,pretty
Platform: UNKNOWN
Classifier: Development Status :: 5 - Production/Stable
Classifier: Intended Audience :: Developers
Classifier: Topic :: Software Development :: Libraries :: Python Modules
Classifier: License :: OSI Approved :: GNU General Public License v3 (GPLv3)
Classifier: Programming Language :: Python :: 2
Classifier: Programming Language :: Python :: 2.7
Classifier: Programming Language :: Python :: 3
Classifier: Programming Language :: Python :: 3.5
Requires-Dist: six
